{
  "_format": "hh3-sol-build-info-1",
  "id": "solc-0_8_28-f5d0044fcb582d68bc11ee055daf11f1c28ae331",
  "solcVersion": "0.8.28",
  "solcLongVersion": "0.8.28+commit.7893614a",
  "userSourceNameMap": {
    "contracts/CrowdFund.sol": "project/contracts/CrowdFund.sol"
  },
  "input": {
    "language": "Solidity",
    "settings": {
      "evmVersion": "cancun",
      "optimizer": {
        "enabled": true,
        "runs": 200
      },
      "outputSelection": {
        "*": {
          "": [
            "ast"
          ],
          "*": [
            "abi",
            "evm.bytecode",
            "evm.deployedBytecode",
            "evm.methodIdentifiers",
            "metadata"
          ]
        }
      },
      "remappings": []
    },
    "sources": {
      "project/contracts/CrowdFund.sol": {
        "content": "// SPDX-License-Identifier: UNLICENSED\r\npragma solidity ^0.8.20;\r\n\r\ncontract CrowdFund {\r\n    address public owner;\r\n    uint public goal;\r\n    uint public totalRaised;\r\n\r\n    constructor(uint _goal) {\r\n        owner = msg.sender;\r\n        goal = _goal;\r\n    }\r\n\r\n    function donate() external payable {\r\n        require(msg.value > 0, \"No zero donations\");\r\n        totalRaised += msg.value;\r\n    }\r\n\r\n    function goalReached() external view returns (bool) {\r\n        return totalRaised >= goal;\r\n    }\r\n}"
      }
    }
  }
}